pwny/__init__.py
little_pwny-0.3.dist-info/LICENSE
little_pwny-0.3.dist-info/METADATA
little_pwny-0.3.dist-info/WHEEL
little_pwny-0.3.dist-info/entry_points.txt
little_pwny-0.3.dist-info/top_level.txt
little_pwny-0.3.dist-info/RECORD
